chances/__init__.py
chances/methods.py
chances/utils.py
chances/hypercube/__init__.py
chances/hypercube/distance.py
chances/hypercube/hycusampling.py
chances/hypercube/indicator.py
chances/hypercube/subset.py
chances/lhs_sudoku/__init__.py
chances/lhs_sudoku/lhs.py
chances/lhs_sudoku/sudoku.py
chances/quantum/__init__.py
chances/quantum/cmd.py
chances/quantum/dev.py
chances/random_org/__init__.py
chances/random_org/random_org.py
chances/sobol/__init__.py
chances/sobol/sobol_seq.py
chances-0.1.9.dist-info/METADATA
chances-0.1.9.dist-info/WHEEL
chances-0.1.9.dist-info/licenses/LICENSE
chances-0.1.9.dist-info/RECORD
