Metadata-Version: 2.3
Name: chances
Version: 0.1.9
Summary: Chances
Project-URL: Download, https://github.com/autonomio/randomizer/
Project-URL: Homepage, http://autonom.io
Author-email: Mikko Kotila <mailme@mikkokotila.com>
Maintainer-email: Mikko Kotila <mailme@mikkokotila.com>
License-Expression: MIT
License-File: LICENSE
Classifier: Intended Audience :: Science/Research
Classifier: License :: OSI Approved :: MIT License
Classifier: Operating System :: MacOS
Classifier: Operating System :: POSIX
Classifier: Operating System :: Unix
Classifier: Programming Language :: Python :: 3.6
Classifier: Topic :: Scientific/Engineering :: Mathematics
Requires-Dist: numpy
Requires-Dist: requests
Requires-Dist: scipy
